tpdne/__init__.py
tpdne/tpdne.py
tpdne-0.1.1.dist-info/METADATA
tpdne-0.1.1.dist-info/WHEEL
tpdne-0.1.1.dist-info/top_level.txt
tpdne-0.1.1.dist-info/RECORD
