Metadata-Version: 2.1
Name: tpdne
Version: 0.1.1
Summary: Get a face that does not exist
Home-page: https://github.com/carl-mundy/tpdne
Author: Carl Mundy
Author-email: 
Maintainer: Carl Mundy
Maintainer-email: 
License: MIT license
Keywords: tpdne
Platform: UNKNOWN
Classifier: Development Status :: 3 - Alpha
Classifier: Intended Audience :: Developers
Classifier: Programming Language :: Python :: 3.6
Requires-Dist: requests
